Vish_STT/__init__.py
speech_to_text_vcb-0.2.dist-info/METADATA
speech_to_text_vcb-0.2.dist-info/WHEEL
speech_to_text_vcb-0.2.dist-info/top_level.txt
speech_to_text_vcb-0.2.dist-info/RECORD
