Metadata-Version: 2.1
Name: speech-to-text-vcb
Version: 0.2
Summary: this is stt file 
Author: Vishal Chandrabhan Bolke
Author-email: bolkevishal10@gmail.com
Requires-Dist: selenium
Requires-Dist: webdriver-manager
